odooly.py
odooly-2.5.2.dist-info/licenses/LICENSE
odooly-2.5.2.dist-info/METADATA
odooly-2.5.2.dist-info/WHEEL
odooly-2.5.2.dist-info/entry_points.txt
odooly-2.5.2.dist-info/top_level.txt
odooly-2.5.2.dist-info/RECORD
