Metadata-Version: 2.4
Name: Odooly
Version: 2.5.2
Summary: Versatile tool for Odoo
Home-page: http://odooly.readthedocs.org/
Author: Florent Xicluna
Author-email: florent.xicluna@gmail.com
License: BSD-3-Clause
Keywords: odoo openerp xml-rpc xmlrpc jsonrpc json2
Platform: any
Classifier: Development Status :: 5 - Production/Stable
Classifier: Environment :: Console
Classifier: Framework :: Odoo
Classifier: Intended Audience :: Developers
Classifier: Operating System :: OS Independent
Classifier: Programming Language :: Python :: 3
Classifier: Programming Language :: Python :: 3.6
Classifier: Programming Language :: Python :: 3.7
Classifier: Programming Language :: Python :: 3.8
Classifier: Programming Language :: Python :: 3.9
Classifier: Programming Language :: Python :: 3.10
Classifier: Programming Language :: Python :: 3.11
Classifier: Programming Language :: Python :: 3.12
Classifier: Programming Language :: Python :: 3.13
Classifier: Programming Language :: Python :: 3.14
Classifier: Topic :: Software Development :: Libraries :: Python Modules
License-File: LICENSE
Dynamic: license-file
